Metadata-Version: 2.1
Name: djforms
Version: 0.0.5
Summary: Django run app
Home-page: https://github.com/pmaigutyak/djforms
Author: Paul Maigutyak
Author-email: pmaigutyak@gmail.com
License: MIT
Download-URL: https://github.com/pmaigutyak/djforms/archive/0.0.5.tar.gz
Platform: UNKNOWN
